LICENCE
README.md
setup.py
mongodantic/__init__.py
mongodantic/aggregation.py
mongodantic/connection.py
mongodantic/exceptions.py
mongodantic/helpers.py
mongodantic/logical.py
mongodantic/models.py
mongodantic/querybuilder.py
mongodantic/queryset.py
mongodantic/session.py
mongodantic/sync_async.py
mongodantic/types.py
mongodantic.egg-info/PKG-INFO
mongodantic.egg-info/SOURCES.txt
mongodantic.egg-info/dependency_links.txt
mongodantic.egg-info/requires.txt
mongodantic.egg-info/top_level.txt
tests/queries/__init__.py
tests/queries/test_aggregation.py
tests/queries/test_basic_operations.py
tests/queries/test_indexes_operation.py
tests/queries/test_queries_with_inners.py
tests/queries/test_raw_queries.py