Metadata-Version: 2.1
Name: mongodantic
Version: 0.2.6b1
Summary: Mongo ODM, based on pydantic and pymongo
Home-page: https://github.com/bzdvdn/mongodantic
Author: bzdvdn
Author-email: bzdv.dn@gmail.com
License: MIT
Requires-Python: >=3.7
License-File: LICENCE
